trailrunner/__init__.py
trailrunner/__main__.py
trailrunner/__version__.py
trailrunner/core.py
trailrunner/py.typed
trailrunner/tests/__init__.py
trailrunner/tests/__main__.py
trailrunner/tests/core.py
trailrunner-1.4.0.dist-info/LICENSE
trailrunner-1.4.0.dist-info/WHEEL
trailrunner-1.4.0.dist-info/METADATA
trailrunner-1.4.0.dist-info/RECORD
