Metadata-Version: 2.1
Name: trailrunner
Version: 1.4.0
Summary: Run things on paths
Author-email: Amethyst Reese <amy@n7.gg>
Requires-Python: >=3.7
Classifier: Development Status :: 5 - Production/Stable
Classifier: Intended Audience :: Developers
Classifier: License :: OSI Approved :: MIT License
Classifier: Topic :: Utilities
Classifier: Typing :: Typed
Requires-Dist: pathspec>=0.8.1
Requires-Dist: attribution==1.6.2 ; extra == "dev"
Requires-Dist: black==22.3.0 ; extra == "dev"
Requires-Dist: click==8.1.3 ; extra == "dev"
Requires-Dist: coverage==6.5 ; extra == "dev"
Requires-Dist: flit==3.7.1 ; extra == "dev"
Requires-Dist: flake8==4.0.1 ; extra == "dev"
Requires-Dist: flake8-bugbear==23.2.13 ; extra == "dev"
Requires-Dist: mypy==1.1.1 ; extra == "dev"
Requires-Dist: rich==13.3.2 ; extra == "dev"
Requires-Dist: ufmt==2.0.1 ; extra == "dev"
Requires-Dist: usort==1.0.5 ; extra == "dev"
Requires-Dist: sphinx==6.1.3 ; extra == "docs"
Requires-Dist: sphinx-mdinclude==0.5.3 ; extra == "docs"
Project-URL: Changelog, https://trailrunner.omnilib.dev/en/latest/changelog.html
Project-URL: Github, https://github.com/omnilib/trailrunner
Project-URL: Home, https://trailrunner.omnilib.dev
Provides-Extra: dev
Provides-Extra: docs
